bbc_tracklist.py
cmdline.py
bbc_radio_tracklisting_downloader-0.0.3.dist-info/DESCRIPTION.rst
bbc_radio_tracklisting_downloader-0.0.3.dist-info/METADATA
bbc_radio_tracklisting_downloader-0.0.3.dist-info/RECORD
bbc_radio_tracklisting_downloader-0.0.3.dist-info/WHEEL
bbc_radio_tracklisting_downloader-0.0.3.dist-info/entry_points.txt
bbc_radio_tracklisting_downloader-0.0.3.dist-info/metadata.json
bbc_radio_tracklisting_downloader-0.0.3.dist-info/top_level.txt
