Metadata-Version: 2.0
Name: bbc-radio-tracklisting-downloader
Version: 0.0.3
Summary: Download BBC radio show tracklistings
Home-page: https://github.com/StevenMaude/bbc-radio-tracklisting-downloader
Author: Steven Maude
Author-email: git@stevenmaude.co.uk
License: GPLv3
Keywords: bbc,radio,tracklisting,playlist,downloader
Platform: UNKNOWN
Classifier: Development Status :: 4 - Beta
Classifier: Intended Audience :: End Users/Desktop
Classifier: Topic :: Utilities
Classifier: License :: OSI Approved :: GNU General Public License v3 (GPLv3)
Classifier: Programming Language :: Python :: 2.7
Classifier: Programming Language :: Python :: 3.4
Classifier: Programming Language :: Python :: 3.5
Requires-Dist: lxml
Requires-Dist: mediafile
Requires-Dist: requests
